{
    "cos_gwtheta": [
        null,
        0.6888608182277379,
        null
    ],
    "cos_inc": [
        null,
        -0.01869313936312278,
        null
    ],
    "gwphi": [
        null,
        0.9813038367700145,
        null
    ],
    "log10_Mc": [
        null,
        8.006297496173765,
        null
    ],
    "log10_fgw": [
        null,
        -7.117173428812233,
        null
    ],
    "log10_h": [
        -15.988214844189201,
        -15.091547878992932,
        -14.506456825548174
    ],
    "phase0": [
        null,
        3.263500859696452,
        null
    ],
    "psi": [
        null,
        2.998347000710825,
        null
    ]
}